SBPGeologyHeron/SBPGeologyHeron.py
SBPGeologyHeron/__init__.py
SBPGeologyHeron-0.0.3.dist-info/LICENSE
SBPGeologyHeron-0.0.3.dist-info/METADATA
SBPGeologyHeron-0.0.3.dist-info/WHEEL
SBPGeologyHeron-0.0.3.dist-info/top_level.txt
SBPGeologyHeron-0.0.3.dist-info/RECORD
