Metadata-Version: 2.1
Name: SBPGeologyHeron
Version: 0.0.3
Summary: A scientific package to solve Heron shortest path problem in geometry
Home-page: UNKNOWN
Author: Mohammad Ghiasvand Mohammadkhani
Author-email: mohammadmohammadkhani82@gmail.com
License: UNKNOWN
Keywords: "Science By Programming","Geometry","Python","Heron shortest path problem"
Platform: UNKNOWN
Classifier: Programming Language :: Python :: 3
Classifier: License :: OSI Approved :: MIT License
Classifier: Operating System :: OS Independent
Requires-Python: >=3.6
License-File: LICENSE
